ghome/__init__.py
ghome/ghome.py
ghome-0.0.3.dist-info/LICENSE
ghome-0.0.3.dist-info/METADATA
ghome-0.0.3.dist-info/WHEEL
ghome-0.0.3.dist-info/entry_points.txt
ghome-0.0.3.dist-info/top_level.txt
ghome-0.0.3.dist-info/RECORD
