Metadata-Version: 2.1
Name: ghome
Version: 0.0.3
Summary: Simple CLI for Google Home & Mini
Home-page: https://github.com/samapriya/ghome
Author: Samapriya Roy
Author-email: samapriya.roy@gmail.com
License: Apache 2.0
Platform: UNKNOWN
Classifier: Development Status :: 3 - Alpha
Classifier: Intended Audience :: Developers
Classifier: Intended Audience :: Science/Research
Classifier: Natural Language :: English
Classifier: License :: OSI Approved :: Apache Software License
Classifier: Programming Language :: Python
Classifier: Programming Language :: Python :: 2.7
Classifier: Programming Language :: Python :: 3.6
Classifier: Operating System :: OS Independent
Classifier: Topic :: Scientific/Engineering :: GIS
Requires-Dist: requests (>=2.20.1)
Requires-Dist: python-nmap (>=0.6.1)
Requires-Dist: glocaltokens (==0.2.3)
Requires-Dist: retrying (>=1.3.3)
